reversionup.py
setup.cfg
setup.py
ReversionUp.egg-info/PKG-INFO
ReversionUp.egg-info/SOURCES.txt
ReversionUp.egg-info/dependency_links.txt
ReversionUp.egg-info/entry_points.txt
ReversionUp.egg-info/not-zip-safe
ReversionUp.egg-info/top_level.txt