Metadata-Version: 1.1
Name: ReversionUp
Version: 0.4.0
Summary: 
